CHANGES.rst
COPYRIGHT.txt
LICENSE.txt
MANIFEST.in
README.rst
bootstrap.py
setup.py
z3c/__init__.py
z3c.recipe.usercrontab.egg-info/PKG-INFO
z3c.recipe.usercrontab.egg-info/SOURCES.txt
z3c.recipe.usercrontab.egg-info/dependency_links.txt
z3c.recipe.usercrontab.egg-info/entry_points.txt
z3c.recipe.usercrontab.egg-info/namespace_packages.txt
z3c.recipe.usercrontab.egg-info/requires.txt
z3c.recipe.usercrontab.egg-info/top_level.txt
z3c/recipe/__init__.py
z3c/recipe/usercrontab/README.rst
z3c/recipe/usercrontab/__init__.py
z3c/recipe/usercrontab/tests.py
z3c/recipe/usercrontab/usercrontab.py