Metadata-Version: 1.1
Name: z3c.recipe.usercrontab
Version: 1.2.1
Summary: User Crontab install buildout recipe
Home-page: https://github.com/reinout/z3c.recipe.usercrontab
Author: Reinout van Rees
Author-email: reinout@vanrees.org
License: ZPL
Platform: UNKNOWN
Classifier: Development Status :: 6 - Mature
Classifier: Framework :: Buildout
Classifier: Intended Audience :: Developers
Classifier: Topic :: Software Development :: Build Tools
Classifier: Topic :: Software Development :: Libraries :: Python Modules
Classifier: License :: OSI Approved :: Zope Public License
Classifier: Programming Language :: Python :: 2.7
Classifier: Programming Language :: Python :: 3
